django_persian_fields/__init__.py
django_persian_fields/drf_fields/iran_mobile_field.py
django_persian_fields/model_fields/__init__.py
django_persian_fields/model_fields/iran_mobile_field.py
django_persian_fields/model_fields/iran_postal_code.py
django_persian_fields/model_fields/lower_case_char_field.py
django_persian_fields/model_fields/national_id_field.py
django_persian_fields/model_fields/only_digit_field.py
django_persian_fields-0.2.3.dist-info/LICENSE
django_persian_fields-0.2.3.dist-info/METADATA
django_persian_fields-0.2.3.dist-info/WHEEL
django_persian_fields-0.2.3.dist-info/top_level.txt
django_persian_fields-0.2.3.dist-info/RECORD
