Metadata-Version: 2.1
Name: django-persian-fields
Version: 0.2.3
Summary: Persian Fields for Django
Author-email: Ali Shekari <alishekari1991@outlook.com>
Project-URL: Homepage, https://github.com/alishekari/django-persian-fields
Project-URL: Issues, https://github.com/alishekari/django-persian-fields/issues
Classifier: Programming Language :: Python :: 3
Classifier: License :: OSI Approved :: MIT License
Classifier: Operating System :: OS Independent
Requires-Python: >=3.10
License-File: LICENSE
Requires-Dist: django>=4.1.5
Requires-Dist: djangorestframework>=3.14.0
